odoo/addons/sale_commission_product_criteria_discount/README.rst
odoo/addons/sale_commission_product_criteria_discount/__init__.py
odoo/addons/sale_commission_product_criteria_discount/__manifest__.py
odoo/addons/sale_commission_product_criteria_discount/demo/demo_data.xml
odoo/addons/sale_commission_product_criteria_discount/i18n/es.po
odoo/addons/sale_commission_product_criteria_discount/i18n/it.po
odoo/addons/sale_commission_product_criteria_discount/i18n/sale_commission_product_criteria_discount.pot
odoo/addons/sale_commission_product_criteria_discount/models/__init__.py
odoo/addons/sale_commission_product_criteria_discount/models/commission.py
odoo/addons/sale_commission_product_criteria_discount/models/res_config_settings.py
odoo/addons/sale_commission_product_criteria_discount/models/sale.py
odoo/addons/sale_commission_product_criteria_discount/readme/CONTRIBUTORS.rst
odoo/addons/sale_commission_product_criteria_discount/readme/DESCRIPTION.rst
odoo/addons/sale_commission_product_criteria_discount/readme/USAGE.rst
odoo/addons/sale_commission_product_criteria_discount/security/base_groups.xml
odoo/addons/sale_commission_product_criteria_discount/static/description/icon.png
odoo/addons/sale_commission_product_criteria_discount/static/description/index.html
odoo/addons/sale_commission_product_criteria_discount/tests/__init__.py
odoo/addons/sale_commission_product_criteria_discount/tests/test_sale_commission_product_criteria.py
odoo/addons/sale_commission_product_criteria_discount/views/res_config_settings_views.xml
odoo/addons/sale_commission_product_criteria_discount/views/views.xml
odoo14_addon_sale_commission_product_criteria_discount-14.0.1.0.3.dist-info/METADATA
odoo14_addon_sale_commission_product_criteria_discount-14.0.1.0.3.dist-info/WHEEL
odoo14_addon_sale_commission_product_criteria_discount-14.0.1.0.3.dist-info/top_level.txt
odoo14_addon_sale_commission_product_criteria_discount-14.0.1.0.3.dist-info/RECORD
